MANIFEST.in
README.md
setup.cfg
setup.py
apg/__init__.py
apg/commands.py
apg/run.py
apg.egg-info/PKG-INFO
apg.egg-info/SOURCES.txt
apg.egg-info/dependency_links.txt
apg.egg-info/entry_points.txt
apg.egg-info/requires.txt
apg.egg-info/top_level.txt
apg/templates/aiohttp/framework/cookiecutter.json
apg/templates/aiohttp/framework/hooks/post_gen_project.py
apg/templates/aiohttp/framework/hooks/pre_gen_project.py
apg/templates/aiohttp/framework/{{cookiecutter.app_name}}/.dockerignore
apg/templates/aiohttp/framework/{{cookiecutter.app_name}}/.gitignore
apg/templates/aiohttp/framework/{{cookiecutter.app_name}}/Dockerfile
apg/templates/aiohttp/framework/{{cookiecutter.app_name}}/Makefile
apg/templates/aiohttp/framework/{{cookiecutter.app_name}}/README.md
apg/templates/aiohttp/framework/{{cookiecutter.app_name}}/alembic.ini
apg/templates/aiohttp/framework/{{cookiecutter.app_name}}/cli.py
apg/templates/aiohttp/framework/{{cookiecutter.app_name}}/config.py
apg/templates/aiohttp/framework/{{cookiecutter.app_name}}/constants.py
apg/templates/aiohttp/framework/{{cookiecutter.app_name}}/docker-compose.dev.yml
apg/templates/aiohttp/framework/{{cookiecutter.app_name}}/docker-compose.test.yml
apg/templates/aiohttp/framework/{{cookiecutter.app_name}}/docker-compose.yml
apg/templates/aiohttp/framework/{{cookiecutter.app_name}}/entrypoint.sh
apg/templates/aiohttp/framework/{{cookiecutter.app_name}}/pylama.ini
apg/templates/aiohttp/framework/{{cookiecutter.app_name}}/requirements.txt
apg/templates/aiohttp/framework/{{cookiecutter.app_name}}/run.py
apg/templates/aiohttp/framework/{{cookiecutter.app_name}}/app/__init__.py
apg/templates/aiohttp/framework/{{cookiecutter.app_name}}/app/common/__init__.py
apg/templates/aiohttp/framework/{{cookiecutter.app_name}}/app/common/schemas.py
apg/templates/aiohttp/framework/{{cookiecutter.app_name}}/app/common/specs.py
apg/templates/aiohttp/framework/{{cookiecutter.app_name}}/app/exampleapp/__init__.py
apg/templates/aiohttp/framework/{{cookiecutter.app_name}}/app/exampleapp/schemas.py
apg/templates/aiohttp/framework/{{cookiecutter.app_name}}/app/exampleapp/specs.py
