Metadata-Version: 1.0
Name: apg
Version: 0.4.7
Summary: Awesome project generation tool
Home-page: https://github.com/n0nSmoker/apg
Author: Y-Bro
Author-email: UNKNOWN
License: UNKNOWN
Keywords: apg,generate project,framework,cookie-cutter
Platform: UNKNOWN
